chswt.py
setup.py
chswt.egg-info/PKG-INFO
chswt.egg-info/SOURCES.txt
chswt.egg-info/dependency_links.txt
chswt.egg-info/pbr.json
chswt.egg-info/top_level.txt