Metadata-Version: 1.1
Name: chswt
Version: 0.0.2
Summary: Channel switcher
Home-page: https://github.com/k0st1an/chswt
Author: Konstantin Kruglov
Author-email: kruglovk@gmail.com
License: Apache License Version 2.0
Keywords: network,route,switcher
Platform: UNKNOWN
Classifier: License :: OSI Approved :: Apache Software License
Classifier: Programming Language :: Python
Classifier: Programming Language :: Python :: 3
Classifier: Programming Language :: Python :: 3.3
Classifier: Programming Language :: Python :: 3.4
Classifier: Programming Language :: Python :: 3.5
Classifier: Programming Language :: Python :: 3 :: Only
